{"retCode":1,"retMsg":"Partial Data Returned: the requested data is out of trial data range","data":[{"secID":"002757.XSHE","publishDate":"2016-10-22","endDate":"2016-09-30","endDateRep":"2016-09-30","partyID":66840,"ticker":"002757","secShortName":"南兴装备","exchangeCD":"XSHE","actPubtime":"2016-10-21 17:16:59","mergedFlag":"1","reportType":"CQ3","fiscalPeriod":"9","accoutingStandards":"CHAS_2007","currencyCD":"CNY","CFrSaleGS":398861931.63,"CFrOthOperateA":2700664.38,"CInfFrOperateA":401562596.01,"CPaidGS":232456393.26,"CPaidToForEmpl":48242544.32,"CPaidForTaxes":41340578.42,"CPaidForOthOpA":22672873.31,"COutfOperateA":344712389.31,"NCFOperateA":56850206.7,"procSellInvest":70000000,"gainInvest":500547.95,"dispFixAssetsOth":16000,"CInfFrInvestA":70516547.95,"purFixAssetsOth":22682111.36,"CPaidInvest":120000000,"COutfFrInvestA":142682111.36,"NCFFrInvestA":-72165563.41,"CFrBorr":10000000,"CInfFrFinanA":10000000,"CPaidForDebts":27500000,"CPaidDivProfInt":13954457.59,"CPaidOthFinanA":50000,"COutfFrFinanA":41504457.59,"NCFFrFinanA":-31504457.59,"NChangeInCash":-46819814.3,"NCEBegBal":239293757.15,"NCEEndBal":192473942.85},{"secID":"002757.XSHE","publishDate":"2016-08-18","endDate":"2016-06-30","endDateRep":"2016-06-30","partyID":66840,"ticker":"002757","secShortName":"南兴装备","exchangeCD":"XSHE","actPubtime":"2016-08-17 21:17:09","mergedFlag":"1","reportType":"S1","fiscalPeriod":"6","accoutingStandards":"CHAS_2007","currencyCD":"CNY","CFrSaleGS":248097679.48,"CFrOthOperateA":2243338.26,"CInfFrOperateA":250341017.74,"CPaidGS":105887004.58,"CPaidToForEmpl":30215338.94,"CPaidForTaxes":25344250.69,"CPaidForOthOpA":14894214.26,"COutfOperateA":176340808.47,"NCFOperateA":74000209.27,"dispFixAssetsOth":16000,"CInfFrInvestA":16000,"purFixAssetsOth":19935785.92,"CPaidInvest":120000000,"COutfFrInvestA":139935785.92,"NCFFrInvestA":-139919785.92,"CFrBorr":10000000,"CInfFrFinanA":10000000,"CPaidForDebts":17000000,"CPaidDivProfInt":7304681,"COutfFrFinanA":24304681,"NCFFrFinanA":-14304681,"NChangeInCash":-80224257.65,"NCEBegBal":239293757.15,"NCEEndBal":159069499.5},{"secID":"002757.XSHE","publishDate":"2016-04-20","endDate":"2016-03-31","endDateRep":"2016-03-31","partyID":66840,"ticker":"002757","secShortName":"南兴装备","exchangeCD":"XSHE","actPubtime":"2016-04-19 21:30:18","mergedFlag":"1","reportType":"Q1","fiscalPeriod":"3","accoutingStandards":"CHAS_2007","currencyCD":"CNY","CFrSaleGS":87197268.9,"CFrOthOperateA":823116.58,"CInfFrOperateA":88020385.48,"CPaidGS":55536059.16,"CPaidToForEmpl":13036471.86,"CPaidForTaxes":8601457.53,"CPaidForOthOpA":7962208.83,"COutfOperateA":85136197.38,"NCFOperateA":2884188.1,"purFixAssetsOth":13911665.35,"COutfFrInvestA":13911665.35,"NCFFrInvestA":-13911665.35,"CPaidDivProfInt":1116042.43,"COutfFrFinanA":1116042.43,"NCFFrFinanA":-1116042.43,"NChangeInCash":-12143519.68,"NCEBegBal":239293757.15,"NCEEndBal":227150237.47},{"secID":"002757.XSHE","publishDate":"2016-04-21","endDate":"2015-12-31","endDateRep":"2015-12-31","partyID":66840,"ticker":"002757","secShortName":"南兴装备","exchangeCD":"XSHE","actPubtime":"2016-04-20 18:13:34","mergedFlag":"1","reportType":"A","fiscalPeriod":"12","accoutingStandards":"CHAS_2007","currencyCD":"CNY","CFrSaleGS":455756103.34,"CFrOthOperateA":2964085.84,"CInfFrOperateA":458720189.18,"CPaidGS":287869737.04,"CPaidToForEmpl":62773659.44,"CPaidForTaxes":50884837.25,"CPaidForOthOpA":25583663.51,"COutfOperateA":427111897.24,"NCFOperateA":31608291.94,"purFixAssetsOth":56522469.98,"COutfFrInvestA":56522469.98,"NCFFrInvestA":-56522469.98,"CFrCapContr":330515000,"CFrBorr":54000000,"CInfFrFinanA":384515000,"CPaidForDebts":167000000,"CPaidDivProfInt":7352120.58,"CPaidOthFinanA":4923302.22,"COutfFrFinanA":179275422.8,"NCFFrFinanA":205239577.2,"NChangeInCash":180325399.16,"NCEBegBal":58968357.99,"NCEEndBal":239293757.15},{"secID":"002757.XSHE","publishDate":"2016-04-20","endDate":"2015-12-31","endDateRep":"2015-12-31","partyID":66840,"ticker":"002757","secShortName":"南兴装备","exchangeCD":"XSHE","actPubtime":"2016-04-19 21:30:02","mergedFlag":"1","reportType":"A","fiscalPeriod":"12","accoutingStandards":"CHAS_2007","currencyCD":"CNY","CFrSaleGS":455756103.34,"CFrOthOperateA":2964085.84,"CInfFrOperateA":458720189.18,"CPaidGS":287869737.04,"CPaidToForEmpl":62773659.44,"CPaidForTaxes":50884837.25,"CPaidForOthOpA":25583663.51,"COutfOperateA":427111897.24,"NCFOperateA":31608291.94,"purFixAssetsOth":56522469.98,"COutfFrInvestA":56522469.98,"NCFFrInvestA":-56522469.98,"CFrCapContr":330515000,"CFrBorr":54000000,"CInfFrFinanA":384515000,"CPaidForDebts":167000000,"CPaidDivProfInt":7352120.58,"CPaidOthFinanA":4923302.22,"COutfFrFinanA":179275422.8,"NCFFrFinanA":205239577.2,"NChangeInCash":180325399.16,"NCEBegBal":58968357.99,"NCEEndBal":239293757.15}]}