{"retCode":1,"retMsg":"Partial Data Returned: the requested data is out of trial data range","data":[{"secID":"300104.XSHE","publishDate":"2016-10-25","endDate":"2016-09-30","endDateRep":"2016-09-30","partyID":38066,"ticker":"300104","secShortName":"乐视网","exchangeCD":"XSHE","actPubtime":"2016-10-24 19:59:33","mergedFlag":"1","reportType":"CQ3","fiscalPeriod":"9","accoutingStandards":"CHAS_2007","currencyCD":"CNY","CFrSaleGS":11833407221.01,"NIncBorrOthFI":60000000,"IFCCashIncr":9307366.4,"refundOfTax":919803.41,"CFrOthOperateA":1210361330.01,"CInfFrOperateA":13113995720.83,"CPaidGS":9859277182.42,"NIncDisburOfLA":574072388.95,"CPaidIFC":805956.48,"CPaidToForEmpl":756657743.04,"CPaidForTaxes":341692556.96,"CPaidForOthOpA":1038054897.72,"COutfOperateA":12570560725.57,"NCFOperateA":543434995.26,"procSellInvest":60000000,"gainInvest":808194.14,"dispFixAssetsOth":20020.88,"CInfFrInvestA":60828215.02,"purFixAssetsOth":4051981602.18,"CPaidInvest":3266138152.21,"COutfFrInvestA":7318119754.39,"NCFFrInvestA":-7257291539.37,"CFrCapContr":8817329587.38,"CFrMinoSSubs":4004379000,"CFrBorr":3116539214.56,"CFrOthFinanA":467194875.35,"CInfFrFinanA":12401063677.29,"CPaidForDebts":1973547510.17,"CPaidDivProfInt":259944743.6,"CPaidOthFinanA":2961284594.68,"COutfFrFinanA":5194776848.45,"NCFFrFinanA":7206286828.84,"forexEffects":1206785.98,"NChangeInCash":493637070.71,"NCEBegBal":2714778115.14,"NCEEndBal":3208415185.85},{"secID":"300104.XSHE","publishDate":"2016-08-20","endDate":"2016-06-30","endDateRep":"2016-06-30","partyID":38066,"ticker":"300104","secShortName":"乐视网","exchangeCD":"XSHE","actPubtime":"2016-08-19 17:31:31","mergedFlag":"1","reportType":"S1","fiscalPeriod":"6","accoutingStandards":"CHAS_2007","currencyCD":"CNY","CFrSaleGS":7889998858.84,"NIncBorrOthFI":60000000,"IFCCashIncr":1446280.58,"CFrOthOperateA":326061122.77,"CInfFrOperateA":8277506262.19,"CPaidGS":6100175876.63,"NIncDisburOfLA":515512521.39,"CPaidIFC":805956.48,"CPaidToForEmpl":459197574.51,"CPaidForTaxes":266228152.25,"CPaidForOthOpA":641396565.49,"COutfOperateA":7988316646.75,"NCFOperateA":289189615.44,"procSellInvest":60000000,"gainInvest":808194.14,"dispFixAssetsOth":12631.58,"CInfFrInvestA":60820825.72,"purFixAssetsOth":1804143859.76,"CPaidInvest":2237985591.75,"COutfFrInvestA":4042129451.51,"NCFFrInvestA":-3981308625.79,"CFrCapContr":3951783125.16,"CFrMinoSSubs":3951783125.16,"CFrBorr":3166133728.01,"CFrOthFinanA":250972432.6,"CInfFrFinanA":7368889285.77,"CPaidForDebts":764485569.03,"CPaidDivProfInt":80322251.3,"CPaidOthFinanA":2220837885.94,"COutfFrFinanA":3065645706.27,"NCFFrFinanA":4303243579.5,"forexEffects":1706390.06,"NChangeInCash":612830959.21,"NCEBegBal":2714778115.14,"NCEEndBal":3327609074.35},{"secID":"300104.XSHE","publishDate":"2016-04-20","endDate":"2016-03-31","endDateRep":"2016-03-31","partyID":38066,"ticker":"300104","secShortName":"乐视网","exchangeCD":"XSHE","actPubtime":"2016-04-19 21:30:18","mergedFlag":"1","reportType":"Q1","fiscalPeriod":"3","accoutingStandards":"CHAS_2007","currencyCD":"CNY","CFrSaleGS":2821414626.26,"CFrOthOperateA":6673057.47,"CInfFrOperateA":2828087683.73,"CPaidGS":2158124310.16,"NIncDisburOfLA":30000000,"CPaidToForEmpl":232441726.8,"CPaidForTaxes":106527170.68,"CPaidForOthOpA":236422018.37,"COutfOperateA":2763515226.01,"NCFOperateA":64572457.72,"dispFixAssetsOth":5134.58,"CFrOthInvestA":60000000,"CInfFrInvestA":60005134.58,"purFixAssetsOth":1078517312.66,"CPaidInvest":4000000,"COutfFrInvestA":1082517312.66,"NCFFrInvestA":-1022512178.08,"CFrCapContr":1002250000,"CFrMinoSSubs":1002250000,"CFrBorr":263287179.49,"CInfFrFinanA":1265537179.49,"CPaidForDebts":368819321.58,"CPaidDivProfInt":23284510.08,"CPaidOthFinanA":24469380.17,"COutfFrFinanA":416573211.83,"NCFFrFinanA":848963967.66,"forexEffects":-1805115.12,"NChangeInCash":-110780867.82,"NCEBegBal":2714778115.14,"NCEEndBal":2603997247.32},{"secID":"300104.XSHE","publishDate":"2016-03-18","endDate":"2015-12-31","endDateRep":"2015-12-31","partyID":38066,"ticker":"300104","secShortName":"乐视网","exchangeCD":"XSHE","actPubtime":"2016-03-17 18:26:42","mergedFlag":"1","reportType":"A","fiscalPeriod":"12","accoutingStandards":"CHAS_2007","currencyCD":"CNY","CFrSaleGS":10044744599.42,"refundOfTax":1127498.5,"CFrOthOperateA":113285059.83,"CInfFrOperateA":10159157157.75,"CPaidGS":7562564647.71,"CPaidToForEmpl":595428336.05,"CPaidForTaxes":257620152.08,"CPaidForOthOpA":867842145.45,"COutfOperateA":9283455281.29,"NCFOperateA":875701876.46,"procSellInvest":56556521.11,"dispFixAssetsOth":4350.68,"CInfFrInvestA":56560871.79,"purFixAssetsOth":2809349736.56,"CPaidInvest":142228000,"CPaidOthInvestA":89733291.83,"COutfFrInvestA":3041311028.39,"NCFFrInvestA":-2984750156.6,"CFrCapContr":47910284.84,"CFrBorr":9046574441.04,"CFrIssueBond":1895260000,"CFrOthFinanA":400933888.89,"CInfFrFinanA":11390678614.77,"CPaidForDebts":6746926238.5,"CPaidDivProfInt":144106767.4,"CPaidOthFinanA":134296501.87,"COutfFrFinanA":7025329507.77,"NCFFrFinanA":4365349107,"forexEffects":11128692.65,"NChangeInCash":2267429519.51,"NCEBegBal":447348595.63,"NCEEndBal":2714778115.14}]}