{"retCode":1,"retMsg":"Partial Data Returned: the requested data is out of trial data range","data":[{"secID":"600375.XSHG","publishDate":"2016-10-29","endDate":"2016-09-30","endDateRep":"2016-09-30","partyID":928,"ticker":"600375","secShortName":"*ST星马","exchangeCD":"XSHG","actPubtime":"2016-10-28 17:10:36","mergedFlag":"1","reportType":"CQ3","fiscalPeriod":"9","accoutingStandards":"CHAS_2007","currencyCD":"CNY","CFrSaleGS":1579169953.75,"refundOfTax":2490859.03,"CFrOthOperateA":141427275.75,"CInfFrOperateA":1723088088.53,"CPaidGS":689473192.4,"CPaidToForEmpl":264242841.83,"CPaidForTaxes":110354964.31,"CPaidForOthOpA":248195148.15,"COutfOperateA":1312266146.69,"NCFOperateA":410821941.84,"dispFixAssetsOth":180512.91,"CFrOthInvestA":15657189.45,"CInfFrInvestA":15837702.36,"purFixAssetsOth":23723013.05,"CPaidInvest":12540000,"COutfFrInvestA":36263013.05,"NCFFrInvestA":-20425310.69,"CFrBorr":1252000000,"CFrOthFinanA":100000000,"CInfFrFinanA":1352000000,"CPaidForDebts":1048000000,"CPaidDivProfInt":103465562.4,"CPaidOthFinanA":496996101.34,"COutfFrFinanA":1648461663.74,"NCFFrFinanA":-296461663.74,"forexEffects":1412158.5,"NChangeInCash":95347125.91,"NCEBegBal":251418497.79,"NCEEndBal":346765623.7},{"secID":"600375.XSHG","publishDate":"2016-08-27","endDate":"2016-06-30","endDateRep":"2016-06-30","partyID":928,"ticker":"600375","secShortName":"*ST星马","exchangeCD":"XSHG","actPubtime":"2016-08-26 16:34:59","mergedFlag":"1","reportType":"S1","fiscalPeriod":"6","accoutingStandards":"CHAS_2007","currencyCD":"CNY","CFrSaleGS":1331091122.45,"refundOfTax":1353644.44,"CFrOthOperateA":123715300.36,"CInfFrOperateA":1456160067.25,"CPaidGS":540423057.24,"CPaidToForEmpl":151537505.92,"CPaidForTaxes":60886016.19,"CPaidForOthOpA":146863340.85,"COutfOperateA":899709920.2,"NCFOperateA":556450147.05,"dispFixAssetsOth":11637.87,"CFrOthInvestA":11112535.51,"CInfFrInvestA":11124173.38,"purFixAssetsOth":17256410.26,"CPaidInvest":12540000,"COutfFrInvestA":29796410.26,"NCFFrInvestA":-18672236.88,"CFrBorr":944000000,"CFrOthFinanA":50000000,"CInfFrFinanA":994000000,"CPaidForDebts":805000000,"CPaidDivProfInt":84061319.12,"CPaidOthFinanA":405070533.47,"COutfFrFinanA":1294131852.59,"NCFFrFinanA":-300131852.59,"forexEffects":1329693.93,"NChangeInCash":238975751.51,"NCEBegBal":251418497.79,"NCEEndBal":490394249.3},{"secID":"600375.XSHG","publishDate":"2016-04-23","endDate":"2016-03-31","endDateRep":"2016-03-31","partyID":928,"ticker":"600375","secShortName":"*ST星马","exchangeCD":"XSHG","actPubtime":"2016-04-22 16:25:50","mergedFlag":"1","reportType":"Q1","fiscalPeriod":"3","accoutingStandards":"CHAS_2007","currencyCD":"CNY","CFrSaleGS":527314957.81,"refundOfTax":1083724.38,"CFrOthOperateA":117841729.96,"CInfFrOperateA":646240412.15,"CPaidGS":245237509.33,"CPaidToForEmpl":85512269.82,"CPaidForTaxes":19478344.27,"CPaidForOthOpA":61959274.72,"COutfOperateA":412187398.14,"NCFOperateA":234053014.01,"dispFixAssetsOth":5738,"CFrOthInvestA":1727760.17,"CInfFrInvestA":1733498.17,"purFixAssetsOth":47624105.29,"CPaidInvest":12540000,"COutfFrInvestA":60164105.29,"NCFFrInvestA":-58430607.12,"CFrBorr":649000000,"CInfFrFinanA":649000000,"CPaidForDebts":570000000,"CPaidDivProfInt":30776482.91,"CPaidOthFinanA":138854175.3,"COutfFrFinanA":739630658.21,"NCFFrFinanA":-90630658.21,"forexEffects":384007.32,"NChangeInCash":85375756,"NCEBegBal":251418497.79,"NCEEndBal":336794253.79},{"secID":"600375.XSHG","publishDate":"2016-04-09","endDate":"2015-12-31","endDateRep":"2015-12-31","partyID":928,"ticker":"600375","secShortName":"*ST星马","exchangeCD":"XSHG","actPubtime":"2016-04-08 19:25:35","mergedFlag":"1","reportType":"A","fiscalPeriod":"12","accoutingStandards":"CHAS_2007","currencyCD":"CNY","CFrSaleGS":2312474207.87,"refundOfTax":81832.04,"CFrOthOperateA":66329989.56,"CInfFrOperateA":2378886029.47,"CPaidGS":1007834821.41,"CPaidToForEmpl":354675752.76,"CPaidForTaxes":142070733.74,"CPaidForOthOpA":356623954.42,"COutfOperateA":1861205262.33,"NCFOperateA":517680767.14,"dispFixAssetsOth":853900.71,"CFrOthInvestA":17847966.83,"CInfFrInvestA":18701867.54,"purFixAssetsOth":394743626.3,"COutfFrInvestA":394743626.3,"NCFFrInvestA":-376041758.76,"CFrBorr":1127000000,"CFrOthFinanA":44433333,"CInfFrFinanA":1171433333,"CPaidForDebts":1056000000,"CPaidDivProfInt":107298763.15,"CPaidOthFinanA":199142721.38,"COutfFrFinanA":1362441484.53,"NCFFrFinanA":-191008151.53,"forexEffects":-5067209.65,"NChangeInCash":-54436352.8,"NCEBegBal":305854850.59,"NCEEndBal":251418497.79}]}