{"retCode":1,"retMsg":"Partial Data Returned: the requested data is out of trial data range","data":[{"secID":"600456.XSHG","publishDate":"2016-10-28","endDate":"2016-09-30","endDateRep":"2016-09-30","partyID":983,"ticker":"600456","secShortName":"宝钛股份","exchangeCD":"XSHG","actPubtime":"2016-10-27 20:27:29","mergedFlag":"1","reportType":"CQ3","fiscalPeriod":"9","accoutingStandards":"CHAS_2007","currencyCD":"CNY","CFrSaleGS":1002389225.24,"refundOfTax":8975888.97,"CFrOthOperateA":20882769.11,"CInfFrOperateA":1032247883.32,"CPaidGS":888372430.84,"CPaidToForEmpl":205444130.26,"CPaidForTaxes":57313829.53,"CPaidForOthOpA":31082566.99,"COutfOperateA":1182212957.62,"NCFOperateA":-149965074.3,"procSellInvest":3826.59,"dispFixAssetsOth":294233.7,"CFrOthInvestA":1024194.37,"CInfFrInvestA":1322254.66,"purFixAssetsOth":4074964.75,"CPaidOthInvestA":343532.68,"COutfFrInvestA":4418497.43,"NCFFrInvestA":-3096242.77,"CFrBorr":1085000000,"CInfFrFinanA":1085000000,"CPaidForDebts":1060000000,"CPaidDivProfInt":67807291.43,"CPaidOthFinanA":143626.66,"COutfFrFinanA":1127950918.09,"NCFFrFinanA":-42950918.09,"forexEffects":2368812.52,"NChangeInCash":-193643422.64,"NCEBegBal":835834908.32,"NCEEndBal":642191485.68},{"secID":"600456.XSHG","publishDate":"2016-08-26","endDate":"2016-06-30","endDateRep":"2016-06-30","partyID":983,"ticker":"600456","secShortName":"宝钛股份","exchangeCD":"XSHG","actPubtime":"2016-08-25 16:08:18","mergedFlag":"1","reportType":"S1","fiscalPeriod":"6","accoutingStandards":"CHAS_2007","currencyCD":"CNY","CFrSaleGS":538792094.28,"refundOfTax":8975888.97,"CFrOthOperateA":16068292.58,"CInfFrOperateA":563836275.83,"CPaidGS":433817274.08,"CPaidToForEmpl":143049516.26,"CPaidForTaxes":33707808.09,"CPaidForOthOpA":20749105.91,"COutfOperateA":631323704.34,"NCFOperateA":-67487428.51,"dispFixAssetsOth":22228.7,"CFrOthInvestA":810494.37,"CInfFrInvestA":832723.07,"purFixAssetsOth":2000938.19,"CPaidOthInvestA":198521,"COutfFrInvestA":2199459.19,"NCFFrInvestA":-1366736.12,"CFrBorr":615000000,"CInfFrFinanA":615000000,"CPaidForDebts":490000000,"CPaidDivProfInt":31572138.93,"COutfFrFinanA":521572138.93,"NCFFrFinanA":93427861.07,"forexEffects":1737373.78,"NChangeInCash":26311070.22,"NCEBegBal":835834908.32,"NCEEndBal":862145978.54},{"secID":"600456.XSHG","publishDate":"2016-04-28","endDate":"2016-03-31","endDateRep":"2016-03-31","partyID":983,"ticker":"600456","secShortName":"宝钛股份","exchangeCD":"XSHG","actPubtime":"2016-04-27 22:31:47","mergedFlag":"1","reportType":"Q1","fiscalPeriod":"3","accoutingStandards":"CHAS_2007","currencyCD":"CNY","CFrSaleGS":202428697.52,"refundOfTax":2567439.14,"CFrOthOperateA":5997052.84,"CInfFrOperateA":210993189.5,"CPaidGS":151650505.23,"CPaidToForEmpl":74470133.12,"CPaidForTaxes":22568888.76,"CPaidForOthOpA":10677633.83,"COutfOperateA":259367160.94,"NCFOperateA":-48373971.44,"dispFixAssetsOth":1755,"CFrOthInvestA":487194.37,"CInfFrInvestA":488949.37,"purFixAssetsOth":1131219.2,"CPaidOthInvestA":32630,"COutfFrInvestA":1163849.2,"NCFFrInvestA":-674899.83,"CFrBorr":190000000,"CInfFrFinanA":190000000,"CPaidForDebts":120000000,"CPaidDivProfInt":15834259.56,"COutfFrFinanA":135834259.56,"NCFFrFinanA":54165740.44,"forexEffects":-717231.52,"NChangeInCash":4399637.65,"NCEBegBal":835834908.32,"NCEEndBal":840234545.97},{"secID":"600456.XSHG","publishDate":"2016-04-28","endDate":"2015-12-31","endDateRep":"2015-12-31","partyID":983,"ticker":"600456","secShortName":"宝钛股份","exchangeCD":"XSHG","actPubtime":"2016-04-27 22:31:49","mergedFlag":"1","reportType":"A","fiscalPeriod":"12","accoutingStandards":"CHAS_2007","currencyCD":"CNY","CFrSaleGS":1288458331.59,"refundOfTax":12737697.03,"CFrOthOperateA":34198450.25,"CInfFrOperateA":1335394478.87,"CPaidGS":883911349.27,"CPaidToForEmpl":293353560.97,"CPaidForTaxes":78624711.74,"CPaidForOthOpA":48305629.08,"COutfOperateA":1304195251.06,"NCFOperateA":31199227.81,"procSellInvest":22964.42,"dispFixAssetsOth":108408.1,"CFrOthInvestA":19010287.37,"CInfFrInvestA":19141659.89,"purFixAssetsOth":11827251.81,"CPaidInvest":20932216.78,"CPaidOthInvestA":93756.2,"COutfFrInvestA":32853224.79,"NCFFrInvestA":-13711564.9,"CFrBorr":1350000000,"CFrOthFinanA":2410000,"CInfFrFinanA":1352410000,"CPaidForDebts":1201650000,"CPaidDivProfInt":156551441.1,"divProfSubsMinoS":3844736.84,"COutfFrFinanA":1358201441.1,"NCFFrFinanA":-5791441.1,"forexEffects":3381027.17,"NChangeInCash":15077248.98,"NCEBegBal":797073021.78,"NCEEndBal":812150270.76}]}