{"retCode":1,"retMsg":"Partial Data Returned: the requested data is out of trial data range","data":[{"secID":"603558.XSHG","publishDate":"2016-10-24","endDate":"2016-09-30","endDateRep":"2016-09-30","partyID":66860,"ticker":"603558","secShortName":"健盛集团","exchangeCD":"XSHG","actPubtime":"2016-10-23 14:02:15","mergedFlag":"1","reportType":"CQ3","fiscalPeriod":"9","accoutingStandards":"CHAS_2007","currencyCD":"CNY","CFrSaleGS":573382299.02,"refundOfTax":62978028.14,"CFrOthOperateA":195052539.53,"CInfFrOperateA":831412866.69,"CPaidGS":396560793.87,"CPaidToForEmpl":115770976.29,"CPaidForTaxes":44998501.92,"CPaidForOthOpA":72704154.66,"COutfOperateA":630034426.74,"NCFOperateA":201378439.95,"dispFixAssetsOth":17094.02,"CInfFrInvestA":17094.02,"purFixAssetsOth":319514497.14,"CPaidOthInvestA":567000000,"COutfFrInvestA":886514497.14,"NCFFrInvestA":-886497403.12,"CFrCapContr":985376000,"CFrBorr":406892442.16,"CInfFrFinanA":1392268442.16,"CPaidForDebts":363807991.2,"CPaidDivProfInt":47774543.8,"CPaidOthFinanA":27750000,"COutfFrFinanA":439332535,"NCFFrFinanA":952935907.16,"forexEffects":1440817.36,"NChangeInCash":269257761.35,"NCEBegBal":66672994.82,"NCEEndBal":335930756.17},{"secID":"603558.XSHG","publishDate":"2016-07-22","endDate":"2016-06-30","endDateRep":"2016-06-30","partyID":66860,"ticker":"603558","secShortName":"健盛集团","exchangeCD":"XSHG","actPubtime":"2016-07-21 16:11:13","mergedFlag":"1","reportType":"S1","fiscalPeriod":"6","accoutingStandards":"CHAS_2007","currencyCD":"CNY","CFrSaleGS":312279804.5,"refundOfTax":49023346.36,"CFrOthOperateA":193268585.78,"CInfFrOperateA":554571736.64,"CPaidGS":225840459.26,"CPaidToForEmpl":85696766.42,"CPaidForTaxes":32092692.97,"CPaidForOthOpA":49785709.58,"COutfOperateA":393415628.23,"NCFOperateA":161156108.41,"dispFixAssetsOth":17094.02,"CInfFrInvestA":17094.02,"purFixAssetsOth":220848726.21,"CPaidOthInvestA":600000000,"COutfFrInvestA":820848726.21,"NCFFrInvestA":-820831632.19,"CFrCapContr":985376000,"CFrBorr":258530702.1,"CInfFrFinanA":1243906702.1,"CPaidForDebts":351921174.8,"CPaidDivProfInt":47981808.39,"CPaidOthFinanA":27750000,"COutfFrFinanA":427652983.19,"NCFFrFinanA":816253718.91,"forexEffects":-1216494.54,"NChangeInCash":155361700.59,"NCEBegBal":66672994.82,"NCEEndBal":222034695.41},{"secID":"603558.XSHG","publishDate":"2016-04-29","endDate":"2016-03-31","endDateRep":"2016-03-31","partyID":66860,"ticker":"603558","secShortName":"健盛集团","exchangeCD":"XSHG","actPubtime":"2016-04-28 23:12:43","mergedFlag":"1","reportType":"Q1","fiscalPeriod":"3","accoutingStandards":"CHAS_2007","currencyCD":"CNY","CFrSaleGS":165374681.4,"refundOfTax":23011538.36,"CFrOthOperateA":143881054.11,"CInfFrOperateA":332267273.87,"CPaidGS":85197586.97,"CPaidToForEmpl":37520067,"CPaidForTaxes":14313822.77,"CPaidForOthOpA":25739677.73,"COutfOperateA":162771154.47,"NCFOperateA":169496119.4,"dispFixAssetsOth":17094.02,"CInfFrInvestA":17094.02,"purFixAssetsOth":159639693.24,"COutfFrInvestA":159639693.24,"NCFFrInvestA":-159622599.22,"CFrCapContr":985376000,"CFrBorr":150000000,"CInfFrFinanA":1135376000,"CPaidForDebts":95176901.2,"CPaidDivProfInt":3719599.94,"CPaidOthFinanA":26000000,"COutfFrFinanA":124896501.14,"NCFFrFinanA":1010479498.86,"forexEffects":-4256579.3,"NChangeInCash":1016096439.74,"NCEBegBal":90939570.46,"NCEEndBal":1107036010.2},{"secID":"603558.XSHG","publishDate":"2016-04-29","endDate":"2015-12-31","endDateRep":"2015-12-31","partyID":66860,"ticker":"603558","secShortName":"健盛集团","exchangeCD":"XSHG","actPubtime":"2016-04-28 23:12:36","mergedFlag":"1","reportType":"A","fiscalPeriod":"12","accoutingStandards":"CHAS_2007","currencyCD":"CNY","CFrSaleGS":699652314.5,"refundOfTax":101981179.38,"CFrOthOperateA":40938671.35,"CInfFrOperateA":842572165.23,"CPaidGS":430618088.79,"CPaidToForEmpl":148661360.09,"CPaidForTaxes":77981296.16,"CPaidForOthOpA":86042693.32,"COutfOperateA":743303438.36,"NCFOperateA":99268726.87,"dispFixAssetsOth":9868,"CInfFrInvestA":9868,"purFixAssetsOth":305680418.85,"COutfFrInvestA":305680418.85,"NCFFrInvestA":-305670550.85,"CFrCapContr":356900000,"CFrBorr":241791572.8,"CFrOthFinanA":26000000,"CInfFrFinanA":624691572.8,"CPaidForDebts":322160264,"CPaidDivProfInt":42584417.31,"CPaidOthFinanA":35625285.68,"COutfFrFinanA":400369966.99,"NCFFrFinanA":224321605.81,"forexEffects":-3283862.32,"NChangeInCash":14635919.51,"NCEBegBal":52037075.31,"NCEEndBal":66672994.82}]}