{"retCode":1,"retMsg":"Partial Data Returned: the requested data is out of trial data range","data":[{"secID":"002729.XSHE","publishDate":"2016-10-24","endDate":"2016-09-30","endDateRep":"2016-09-30","partyID":65986,"ticker":"002729","secShortName":"好利来","exchangeCD":"XSHE","actPubtime":"2016-10-23 17:04:49","mergedFlag":"1","reportType":"Q3","fiscalPeriod":"3","accoutingStandards":"CHAS_2007","currencyCD":"CNY","tRevenue":38610011.83,"revenue":38610011.83,"TCogs":29754068.16,"COGS":20980160.16,"bizTaxSurchg":322418.59,"sellExp":1936974.4,"adminExp":6633200.65,"finanExp":-153924.78,"assetsImpairLoss":35239.14,"operateProfit":8855943.67,"NoperateIncome":895822.72,"NoperateExp":9469.75,"TProfit":9742296.64,"incomeTax":1510421.39,"NIncome":8231875.25,"NIncomeAttrP":8231875.25,"basicEPS":0.123,"dilutedEPS":0.123,"othComprIncome":132469.4,"TComprIncome":8364344.65,"comprIncAttrP":8364344.65},{"secID":"002729.XSHE","publishDate":"2016-10-24","endDate":"2016-09-30","endDateRep":"2016-09-30","partyID":65986,"ticker":"002729","secShortName":"好利来","exchangeCD":"XSHE","actPubtime":"2016-10-23 17:04:49","mergedFlag":"1","reportType":"CQ3","fiscalPeriod":"9","accoutingStandards":"CHAS_2007","currencyCD":"CNY","tRevenue":114479025.91,"revenue":114479025.91,"TCogs":99608205.34,"COGS":69606925.74,"bizTaxSurchg":1038955.99,"sellExp":6095785.94,"adminExp":21811695.88,"finanExp":925886.53,"assetsImpairLoss":128955.26,"investIncome":1932149.65,"operateProfit":16802970.22,"NoperateIncome":1434730.12,"NoperateExp":336696.75,"NCADisploss":316746.65,"TProfit":17901003.59,"incomeTax":2844286.44,"NIncome":15056717.15,"NIncomeAttrP":15056717.15,"basicEPS":0.226,"dilutedEPS":0.226,"othComprIncome":458214.76,"TComprIncome":15514931.91,"comprIncAttrP":15514931.91},{"secID":"002729.XSHE","publishDate":"2016-08-24","endDate":"2016-06-30","endDateRep":"2016-06-30","partyID":65986,"ticker":"002729","secShortName":"好利来","exchangeCD":"XSHE","actPubtime":"2016-08-23 16:59:17","mergedFlag":"1","reportType":"S1","fiscalPeriod":"6","accoutingStandards":"CHAS_2007","currencyCD":"CNY","tRevenue":75869014.08,"revenue":75869014.08,"TCogs":69854137.18,"COGS":48626765.58,"bizTaxSurchg":716537.4,"sellExp":4158811.54,"adminExp":15178495.23,"finanExp":1079811.31,"assetsImpairLoss":93716.12,"investIncome":1932149.65,"operateProfit":7947026.55,"NoperateIncome":538907.4,"NoperateExp":327227,"NCADisploss":316746.65,"TProfit":8158706.95,"incomeTax":1333865.05,"NIncome":6824841.9,"NIncomeAttrP":6824841.9,"basicEPS":0.1024,"dilutedEPS":0.1024,"othComprIncome":325745.36,"TComprIncome":7150587.26,"comprIncAttrP":7150587.26},{"secID":"002729.XSHE","publishDate":"2016-04-25","endDate":"2016-03-31","endDateRep":"2016-03-31","partyID":65986,"ticker":"002729","secShortName":"好利来","exchangeCD":"XSHE","actPubtime":"2016-04-24 19:34:41","mergedFlag":"1","reportType":"Q1","fiscalPeriod":"3","accoutingStandards":"CHAS_2007","currencyCD":"CNY","tRevenue":31354817.59,"revenue":31354817.59,"TCogs":30385442.23,"COGS":19120946.27,"bizTaxSurchg":486100.09,"sellExp":2057797.01,"adminExp":7924716.82,"finanExp":735890.44,"assetsImpairLoss":59991.6,"investIncome":695342.47,"operateProfit":1664717.83,"NoperateIncome":21029.79,"NoperateExp":29589.51,"NCADisploss":19589.51,"TProfit":1656158.11,"incomeTax":274280.18,"NIncome":1381877.93,"NIncomeAttrP":1381877.93,"basicEPS":0.02,"dilutedEPS":0.02,"othComprIncome":-83597.1,"TComprIncome":1298280.83,"comprIncAttrP":1298280.83},{"secID":"002729.XSHE","publishDate":"2016-04-25","endDate":"2015-12-31","endDateRep":"2015-12-31","partyID":65986,"ticker":"002729","secShortName":"好利来","exchangeCD":"XSHE","actPubtime":"2016-04-24 19:34:41","mergedFlag":"1","reportType":"A","fiscalPeriod":"12","accoutingStandards":"CHAS_2007","currencyCD":"CNY","tRevenue":156938258.93,"revenue":156938258.93,"TCogs":125797021.04,"COGS":89877130.57,"bizTaxSurchg":1412686.69,"sellExp":11093760.43,"adminExp":25418949.02,"finanExp":-1626058.67,"assetsImpairLoss":-379447,"investIncome":3210708.9,"operateProfit":34351946.79,"NoperateIncome":1993560.58,"NoperateExp":1725179.62,"NCADisploss":1390773.73,"TProfit":34620327.75,"incomeTax":4906843.23,"NIncome":29713484.52,"NIncomeAttrP":29713484.52,"basicEPS":0.45,"dilutedEPS":0.45,"othComprIncome":846395.55,"TComprIncome":30559880.07,"comprIncAttrP":30559880.07}]}