{"retCode":1,"retMsg":"Partial Data Returned: the requested data is out of trial data range","data":[{"secID":"600130.XSHG","publishDate":"2016-10-29","endDate":"2016-09-30","endDateRep":"2016-09-30","partyID":712,"ticker":"600130","secShortName":"波导股份","exchangeCD":"XSHG","actPubtime":"2016-10-28 20:31:27","mergedFlag":"1","reportType":"Q3","fiscalPeriod":"9","accoutingStandards":"CHAS_2007","currencyCD":"CNY","cashCEquiv":200982835.78,"NotesReceiv":2351898.9,"AR":125084077.26,"prepayment":27209587.53,"othReceiv":109142908.23,"inventories":295091834.18,"NCAWithin1Y":50000000,"othCA":232036970.71,"TCA":1041900112.59,"availForSaleFa":60720000,"LTEquityInvest":14540389.42,"investRealEstate":143710288.6,"fixedAssets":105023025.91,"intanAssets":14088222.76,"TNCA":338081926.69,"TAssets":1379982039.28,"STBorr":23372300,"AP":253839077.95,"advanceReceipts":61255414.12,"payrollPayable":32285865.59,"taxesPayable":4944796.79,"intPayable":56140.78,"othPayable":9782114.04,"TCL":385535709.27,"LTPayable":1181816,"TNCL":8181628.57,"TLiab":393717337.84,"paidInCapital":768000000,"capitalReser":455922182.76,"surplusReser":66404174.11,"retainedEarnings":-308985677.78,"TEquityAttrP":986264701.44,"TShEquity":986264701.44,"TLiabEquity":1379982039.28},{"secID":"600130.XSHG","publishDate":"2016-08-30","endDate":"2016-06-30","endDateRep":"2016-06-30","partyID":712,"ticker":"600130","secShortName":"波导股份","exchangeCD":"XSHG","actPubtime":"2016-08-29 16:19:05","mergedFlag":"1","reportType":"S1","fiscalPeriod":"6","accoutingStandards":"CHAS_2007","currencyCD":"CNY","cashCEquiv":119656389.5,"AR":138873655.48,"prepayment":5642165.5,"othReceiv":153409183.55,"inventories":258887963.61,"NCAWithin1Y":50000000,"othCA":317652403.39,"TCA":1044121761.03,"availForSaleFa":60720000,"investRealEstate":145551268.66,"fixedAssets":106245090.74,"intanAssets":14210775,"othNCA":810000,"TNCA":327537134.4,"TAssets":1371658895.43,"STBorr":45092160,"AP":252898083.02,"advanceReceipts":41804901.21,"payrollPayable":28163078.18,"taxesPayable":5835313.28,"intPayable":62333.04,"othPayable":9674695.53,"TCL":383530564.26,"LTPayable":1181816,"TNCL":8321550.33,"TLiab":391852114.59,"paidInCapital":768000000,"capitalReser":455922182.76,"surplusReser":66404174.11,"retainedEarnings":-315474077.81,"TEquityAttrP":979806780.84,"TShEquity":979806780.84,"TLiabEquity":1371658895.43},{"secID":"600130.XSHG","publishDate":"2016-04-30","endDate":"2016-03-31","endDateRep":"2016-03-31","partyID":712,"ticker":"600130","secShortName":"波导股份","exchangeCD":"XSHG","actPubtime":"2016-04-29 16:40:29","mergedFlag":"1","reportType":"Q1","fiscalPeriod":"3","accoutingStandards":"CHAS_2007","currencyCD":"CNY","cashCEquiv":232734911.64,"AR":116987189.19,"prepayment":7838654.64,"othReceiv":129129749.53,"inventories":402545243.43,"NCAWithin1Y":50000000,"othCA":332417560.67,"TCA":1271653309.1,"investRealEstate":147391515.98,"fixedAssets":97643716.84,"intanAssets":14338885.57,"othNCA":810000,"TNCA":260184118.39,"TAssets":1531837427.49,"STBorr":18091360,"AP":431784417.02,"advanceReceipts":56915796.9,"payrollPayable":24901518.11,"taxesPayable":6483482.18,"intPayable":37507.33,"othPayable":9946461.24,"TCL":548160542.78,"LTPayable":1181816,"TNCL":8465625.89,"TLiab":556626168.67,"paidInCapital":768000000,"capitalReser":455922182.76,"surplusReser":66404174.11,"retainedEarnings":-320171830.95,"TEquityAttrP":975211258.82,"TShEquity":975211258.82,"TLiabEquity":1531837427.49},{"secID":"600130.XSHG","publishDate":"2016-10-29","endDate":"2015-12-31","endDateRep":"2016-09-30","partyID":712,"ticker":"600130","secShortName":"波导股份","exchangeCD":"XSHG","actPubtime":"2016-10-28 20:31:27","mergedFlag":"1","reportType":"A","fiscalPeriod":"12","accoutingStandards":"CHAS_2007","currencyCD":"CNY","cashCEquiv":403138164.91,"NotesReceiv":50000,"AR":79757897.83,"prepayment":17959438.22,"othReceiv":144115334.46,"inventories":156461880.35,"NCAWithin1Y":50000000,"othCA":259436438.52,"TCA":1110919154.29,"investRealEstate":149231764.29,"fixedAssets":101222282.35,"intanAssets":14466996.13,"othNCA":810000,"TNCA":265731042.77,"TAssets":1376650197.06,"STBorr":47403280,"AP":258789466.24,"advanceReceipts":54056981.97,"payrollPayable":26392288.35,"taxesPayable":6563746.9,"intPayable":37949.11,"othPayable":10185068.2,"TCL":403428780.77,"LTPayable":1181816,"TNCL":8577519.65,"TLiab":412006300.42,"paidInCapital":768000000,"capitalReser":455922182.76,"surplusReser":66404174.11,"retainedEarnings":-330717845.77,"TEquityAttrP":964643896.64,"TShEquity":964643896.64,"TLiabEquity":1376650197.06},{"secID":"600130.XSHG","publishDate":"2016-08-30","endDate":"2015-12-31","endDateRep":"2016-06-30","partyID":712,"ticker":"600130","secShortName":"波导股份","exchangeCD":"XSHG","actPubtime":"2016-08-29 16:19:05","mergedFlag":"1","reportType":"A","fiscalPeriod":"12","accoutingStandards":"CHAS_2007","currencyCD":"CNY","cashCEquiv":403138164.91,"NotesReceiv":50000,"AR":79757897.83,"prepayment":17959438.22,"othReceiv":144115334.46,"inventories":156461880.35,"NCAWithin1Y":50000000,"othCA":259436438.52,"TCA":1110919154.29,"investRealEstate":149231764.29,"fixedAssets":101222282.35,"intanAssets":14466996.13,"othNCA":810000,"TNCA":265731042.77,"TAssets":1376650197.06,"STBorr":47403280,"AP":258789466.24,"advanceReceipts":54056981.97,"payrollPayable":26392288.35,"taxesPayable":6563746.9,"intPayable":37949.11,"othPayable":10185068.2,"TCL":403428780.77,"LTPayable":1181816,"TNCL":8577519.65,"TLiab":412006300.42,"paidInCapital":768000000,"capitalReser":455922182.76,"surplusReser":66404174.11,"retainedEarnings":-330717845.77,"TEquityAttrP":964643896.64,"TShEquity":964643896.64,"TLiabEquity":1376650197.06},{"secID":"600130.XSHG","publishDate":"2016-04-30","endDate":"2015-12-31","endDateRep":"2016-03-31","partyID":712,"ticker":"600130","secShortName":"波导股份","exchangeCD":"XSHG","actPubtime":"2016-04-29 16:40:29","mergedFlag":"1","reportType":"A","fiscalPeriod":"12","accoutingStandards":"CHAS_2007","currencyCD":"CNY","cashCEquiv":403138164.91,"NotesReceiv":50000,"AR":79757897.83,"prepayment":17959438.22,"othReceiv":144115334.46,"inventories":156461880.35,"NCAWithin1Y":50000000,"othCA":259436438.52,"TCA":1110919154.29,"investRealEstate":149231764.29,"fixedAssets":101222282.35,"intanAssets":14466996.13,"othNCA":810000,"TNCA":265731042.77,"TAssets":1376650197.06,"STBorr":47403280,"AP":258789466.24,"advanceReceipts":54056981.97,"payrollPayable":26392288.35,"taxesPayable":6563746.9,"intPayable":37949.11,"othPayable":10185068.2,"TCL":403428780.77,"LTPayable":1181816,"TNCL":8577519.65,"TLiab":412006300.42,"paidInCapital":768000000,"capitalReser":455922182.76,"surplusReser":66404174.11,"retainedEarnings":-330717845.77,"TEquityAttrP":964643896.64,"TShEquity":964643896.64,"TLiabEquity":1376650197.06},{"secID":"600130.XSHG","publishDate":"2016-03-29","endDate":"2015-12-31","endDateRep":"2015-12-31","partyID":712,"ticker":"600130","secShortName":"波导股份","exchangeCD":"XSHG","actPubtime":"2016-03-28 20:17:05","mergedFlag":"1","reportType":"A","fiscalPeriod":"12","accoutingStandards":"CHAS_2007","currencyCD":"CNY","cashCEquiv":403138164.91,"NotesReceiv":50000,"AR":79757897.83,"prepayment":17959438.22,"othReceiv":144115334.46,"inventories":156461880.35,"NCAWithin1Y":50000000,"othCA":259436438.52,"TCA":1110919154.29,"investRealEstate":149231764.29,"fixedAssets":101222282.35,"intanAssets":14466996.13,"othNCA":810000,"TNCA":265731042.77,"TAssets":1376650197.06,"STBorr":47403280,"AP":258789466.24,"advanceReceipts":54056981.97,"payrollPayable":26392288.35,"taxesPayable":6563746.9,"intPayable":37949.11,"othPayable":10185068.2,"TCL":403428780.77,"LTPayable":1181816,"TNCL":8577519.65,"TLiab":412006300.42,"paidInCapital":768000000,"capitalReser":455922182.76,"surplusReser":66404174.11,"retainedEarnings":-330717845.77,"TEquityAttrP":964643896.64,"TShEquity":964643896.64,"TLiabEquity":1376650197.06}]}